odoo/addons/mail_channel_follow_model/LICENSE
odoo/addons/mail_channel_follow_model/README.rst
odoo/addons/mail_channel_follow_model/__init__.py
odoo/addons/mail_channel_follow_model/__manifest__.py
odoo/addons/mail_channel_follow_model/demo/mail_channel_followers_demo.xml
odoo/addons/mail_channel_follow_model/i18n/de.po
odoo/addons/mail_channel_follow_model/images/screen.png
odoo/addons/mail_channel_follow_model/models/__init__.py
odoo/addons/mail_channel_follow_model/models/ir_model.py
odoo/addons/mail_channel_follow_model/models/mail_channel.py
odoo/addons/mail_channel_follow_model/models/mail_channel_followers.py
odoo/addons/mail_channel_follow_model/models/mail_thread.py
odoo/addons/mail_channel_follow_model/readme/CONTRIBUTORS.md
odoo/addons/mail_channel_follow_model/readme/DESCRIPTION.md
odoo/addons/mail_channel_follow_model/readme/USAGE.md
odoo/addons/mail_channel_follow_model/security/ir.model.access.csv
odoo/addons/mail_channel_follow_model/static/description/icon.png
odoo/addons/mail_channel_follow_model/static/description/index.html
odoo/addons/mail_channel_follow_model/tests/TEST_INSTRUCTIONS.rst
odoo/addons/mail_channel_follow_model/tests/__init__.py
odoo/addons/mail_channel_follow_model/tests/test_mail_channel_follow_model.py
odoo/addons/mail_channel_follow_model/views/mail_channel_views.xml
odoo_addon_mail_channel_follow_model-18.0.1.0.0.dist-info/METADATA
odoo_addon_mail_channel_follow_model-18.0.1.0.0.dist-info/WHEEL
odoo_addon_mail_channel_follow_model-18.0.1.0.0.dist-info/top_level.txt
odoo_addon_mail_channel_follow_model-18.0.1.0.0.dist-info/RECORD
